healthchecks_io/__init__.py
healthchecks_io/client/__init__.py
healthchecks_io/client/_abstract.py
healthchecks_io/client/async_client.py
healthchecks_io/client/check_trap.py
healthchecks_io/client/exceptions.py
healthchecks_io/client/sync_client.py
healthchecks_io/py.typed
healthchecks_io/schemas/__init__.py
healthchecks_io/schemas/badges.py
healthchecks_io/schemas/checks.py
healthchecks_io/schemas/integrations.py
healthchecks_io-0.4.4.dist-info/LICENSE
healthchecks_io-0.4.4.dist-info/LICENSE.rst
healthchecks_io-0.4.4.dist-info/METADATA
healthchecks_io-0.4.4.dist-info/WHEEL
healthchecks_io-0.4.4.dist-info/RECORD
