Metadata-Version: 2.1
Name: healthchecks_io
Version: 0.4.4
Summary: A python client package for Healthchecks.io API
Home-page: https://github.com/andrewthetechie/py-healthchecks.io
License: MIT
Author: Andrew Herrington
Author-email: andrew.the.techie@gmail.com
Requires-Python: >=3.8,<4.0
Classifier: Development Status :: 4 - Beta
Classifier: Framework :: AsyncIO
Classifier: Intended Audience :: Developers
Classifier: License :: OSI Approved :: MIT License
Classifier: Programming Language :: Python
Classifier: Programming Language :: Python :: 3
Classifier: Programming Language :: Python :: 3.8
Classifier: Programming Language :: Python :: 3.9
Classifier: Programming Language :: Python :: 3.10
Classifier: Programming Language :: Python :: 3.11
Classifier: Programming Language :: Python :: 3.12
Classifier: Programming Language :: Python :: 3.13
Classifier: Programming Language :: Python :: 3.7
Requires-Dist: croniter (>=1.1,<4.0)
Requires-Dist: httpx (>=0.23.0,<0.28.0)
Requires-Dist: packaging (>=24.1,<25.0)
Requires-Dist: pydantic (>=1.9.1,<3.0.0)
Requires-Dist: pytz (>=2024.1,<2025.0)
Project-URL: Changelog, https://github.com/andrewthetechie/py-healthchecks.io/releases
Project-URL: Documentation, https://py-healthchecksio.readthedocs.io
Project-URL: Repository, https://github.com/andrewthetechie/py-healthchecks.io
